[
    {
        "podcastName": "Flow Podcast",
        "episode": "CBUM - Flow #319",
        "videoId": "pQSuQmUfS30",
        "category": ["bodybuilder", "fitness"]
    },
    {
        "podcastName": "Flow Podcast",
        "episode": "RUBENS BARRICHELLO - Flow #339",
        "videoId": "4KDGTdiOV4I",
        "category": ["bodybuilder", "corrida"]
    },
    {
        "podcastName": "Flow Podcast",
        "episode": "Pedro Lira - Flow #400",
        "videoId": "7iDHTdFOV3I",
        "category": ["bodybuilder", "corrida"]
    }
]